opendata_transport/__init__.py
opendata_transport/exceptions.py
python_opendata_transport-0.3.0.dist-info/LICENSE
python_opendata_transport-0.3.0.dist-info/METADATA
python_opendata_transport-0.3.0.dist-info/WHEEL
python_opendata_transport-0.3.0.dist-info/top_level.txt
python_opendata_transport-0.3.0.dist-info/zip-safe
python_opendata_transport-0.3.0.dist-info/RECORD
